Aluora/__init__.py
Aluora/core/__init__.py
Aluora/core/extractor.py
Aluora/models/__init__.py
Aluora/models/bart_cnn.py
Aluora/models/llm_base.py
Aluora/models/simple_densenet.py
aluora-1.0.6.dist-info/METADATA
aluora-1.0.6.dist-info/WHEEL
aluora-1.0.6.dist-info/top_level.txt
aluora-1.0.6.dist-info/RECORD
