Metadata-Version: 2.4
Name: Aluora
Version: 1.0.6
Summary: Librería para detectar alucinaciones
Home-page: https://github.com/Pedro-Sarmiento
Author: Pedro Sarmiento
Author-email: pedro.sarmiento102@alu.ulpgc.es
License: MIT
Dynamic: author
Dynamic: author-email
Dynamic: description
Dynamic: description-content-type
Dynamic: home-page
Dynamic: license
Dynamic: summary
